cyluhn.cpython-312-i386-linux-gnu.so
cyluhn-0.2.1.dist-info/top_level.txt
cyluhn-0.2.1.dist-info/WHEEL
cyluhn-0.2.1.dist-info/entry_points.txt
cyluhn-0.2.1.dist-info/METADATA
cyluhn-0.2.1.dist-info/LICENSE
cyluhn-0.2.1.dist-info/RECORD
